discord_rich_help/__init__.py
discord_rich_help/help.py
discord_rich_help/py.typed
discord_rich_help/text.py
discord_rich_help/ui.py
discord_rich_help.py-0.1.1.dist-info/LICENSE
discord_rich_help.py-0.1.1.dist-info/METADATA
discord_rich_help.py-0.1.1.dist-info/WHEEL
discord_rich_help.py-0.1.1.dist-info/top_level.txt
discord_rich_help.py-0.1.1.dist-info/RECORD
