Metadata-Version: 2.1
Name: discord-rich-help.py
Version: 0.1.1
Summary: An extension which makes a rich-help command for discord.py
Author-email: PescadoGames <official@pescadogames.com>
Maintainer-email: Awayume <dev@awayume.jp>
License: MIT License
Project-URL: Repository, https://github.com/PescadoGames/discord-rich-help.py
Project-URL: Documentation, https://github.com/PescadoGames/discord-rich-help.py/wiki
Project-URL: Bug Tracker, https://github.com/PescadoGames/discord_rich_help.py/issues
Keywords: discord,discord.py
Classifier: Development Status :: 2 - Pre-Alpha
Classifier: Intended Audience :: Developers
Classifier: License :: OSI Approved :: MIT License
Classifier: Environment :: Plugins
Classifier: Natural Language :: English
Classifier: Operating System :: OS Independent
Classifier: Programming Language :: Python :: 3.8
Classifier: Programming Language :: Python :: 3.9
Classifier: Programming Language :: Python :: 3.10
Classifier: Programming Language :: Python :: 3.11
Classifier: Topic :: Internet
Classifier: Topic :: Software Development :: Libraries
Classifier: Topic :: Software Development :: Libraries :: Python Modules
Classifier: Topic :: Utilities
Classifier: Typing :: Typed
Requires-Python: >=3.8
License-File: LICENSE
Provides-Extra: build
Requires-Dist: discord.py (<3.0.0,>=2.2.2) ; extra == 'build'
Provides-Extra: test
Requires-Dist: discord.py (<3.0.0,>=2.2.2) ; extra == 'test'
Requires-Dist: flake8 (<7.0.0,>=6.0.0) ; extra == 'test'
Requires-Dist: flake8-deprecated (<3.0.0,>=2.0.0) ; extra == 'test'
Requires-Dist: flake8-docstrings (<2.0.0,>=1.7.0) ; extra == 'test'
Requires-Dist: flake8-import-order (<0.19.0,>=0.18.2) ; extra == 'test'
Requires-Dist: flake8-print (<6.0.0,>=5.0.0) ; extra == 'test'
Requires-Dist: flake8-quotes (<4.0.0,>=3.3.2) ; extra == 'test'
Requires-Dist: pyproject-flake8 (<7.0.0,>=6.0.0) ; extra == 'test'
Requires-Dist: mypy (<2.0.0,>=1.1.1) ; extra == 'test'
Requires-Dist: typing-extensions (<5.0.0,>=4.5.0) ; extra == 'test'
Requires-Dist: pytest (<8.0.0,>=7.2.2) ; extra == 'test'
Requires-Dist: pytest-mock (<4.0.0,>=3.10.0) ; extra == 'test'
